otp_logatta_django/__init__.py
otp_logatta_django/apps.py
otp_logatta_django/setup.py
otp_logatta_django/urls.py
otp_logatta_django/utils.py
otp_logatta_django/views.py
otp_logatta_django-0.0.8.dist-info/LICENSE
otp_logatta_django-0.0.8.dist-info/METADATA
otp_logatta_django-0.0.8.dist-info/WHEEL
otp_logatta_django-0.0.8.dist-info/top_level.txt
otp_logatta_django-0.0.8.dist-info/RECORD
